unpoly/__init__.py
unpoly/adapter.py
unpoly/options.py
unpoly/up.py
unpoly/contrib/__init__.py
unpoly/contrib/django.py
unpoly-3.0.0.dist-info/METADATA
unpoly-3.0.0.dist-info/WHEEL
unpoly-3.0.0.dist-info/licenses/LICENSE
unpoly-3.0.0.dist-info/RECORD
