Metadata-Version: 2.1
Name: unpoly
Version: 3.0.0
Summary: Framework agnostic implementation of the unpoly server-protocol.
Project-URL: Homepage, https://gitlab.com/rocketduck/python-unpoly
Project-URL: Documentation, https://unpoly.readthedocs.io/en/latest
Author-email: Florian Apolloner <florian@apolloner.eu>
License: BSD-2-Clause
License-File: LICENSE
Classifier: Environment :: Web Environment
Classifier: Framework :: Django
Classifier: Intended Audience :: Developers
Classifier: License :: OSI Approved :: BSD License
Classifier: Operating System :: OS Independent
Classifier: Programming Language :: Python
Classifier: Programming Language :: Python :: 3
Classifier: Programming Language :: Python :: 3 :: Only
Classifier: Programming Language :: Python :: 3.8
Classifier: Programming Language :: Python :: 3.9
Classifier: Programming Language :: Python :: 3.10
Classifier: Programming Language :: Python :: 3.11
Classifier: Programming Language :: Python :: 3.12
Classifier: Topic :: Internet :: WWW/HTTP
Classifier: Topic :: Software Development :: Libraries :: Application Frameworks
Classifier: Topic :: Software Development :: Libraries :: Python Modules
Requires-Python: >=3.8
Requires-Dist: attrs>=21.4.0
